cronaion
