Metadata-Version: 2.1
Name: cronaion
Version: 1.0.4
Summary: Scheduler for python tasks.
Home-page: UNKNOWN
Author: Chris Reusch
License: UNKNOWN
Platform: UNKNOWN
